{"cameraMode":{"drawMode":0,"name":"Shaded","section":"Shading Mode"},"sceneLighting":false,"audioPlay":false,"sceneViewState":{"showFog":true,"showMaterialUpdate":false,"showSkybox":false,"showFlares":true,"showImageEffects":true,"showParticleSystems":true,"showVisualEffectGraphs":true,"m_FxEnabled":true},"in2DMode":false,"pivot":{"x":-17.535568237304689,"y":2.2529778480529787,"z":6.324847221374512},"rotation":{"x":-0.016573229804635049,"y":-0.5657632350921631,"z":-0.011375118978321553,"w":0.8243178129196167},"size":11.83807373046875,"orthographic":false}